[
  {
    "id": "consign",
    "date": "2026-06-18",
    "title": "เปิดรับฝากขายพระเครื่อง",
    "summary": "มีพระอยากปล่อย ส่งรูปและรายละเอียดมาทาง LINE ทีมงานช่วยประเมิน ลงประกาศ และแจ้งเมื่อมีผู้สนใจ",
    "tag": "บริการ"
  },
  {
    "id": "launch",
    "date": "2026-06-18",
    "title": "เปิดให้บริการ Ener Scan รับอ่านพลังงานผ่าน LINE",
    "summary": "สแกนพระเครื่อง เครื่องราง หินและคริสตัล ได้สรุปผลเบื้องต้นในแชต พร้อมรายงานฉบับเต็มบนเว็บ",
    "tag": "ประกาศ"
  },
  {
    "id": "howto",
    "date": "2026-06-18",
    "title": "วิธีเริ่มสแกน — แอดเพื่อน LINE แล้วส่งรูปวัตถุ",
    "summary": "สแกน QR ด้านล่างหน้าแรก หรือกดปุ่มแอดเพื่อน จากนั้นส่งรูปวัตถุชัดๆ วัตถุละ 1 รูปต่อครั้ง",
    "tag": "คู่มือ"
  },
  {
    "id": "free-quota",
    "date": "2026-06-18",
    "title": "มีโควตาสแกนฟรีให้ลองทุกวัน",
    "summary": "ผู้ใช้ใหม่สามารถลองสแกนฟรีได้ก่อนตัดสินใจ หากต้องการสแกนเพิ่มสามารถชำระผ่าน PromptPay ในแชต",
    "tag": "บริการ"
  }
]
